setup.py
pylcc/__init__.py
pylcc/clcc.py
pylcc/lbcBase.py
pylcc/lbcInclude.py
pylcc/lbcMaps.py
pylcc/lbcStack.py
pylcc/perfEvent.py
pylcc.egg-info/PKG-INFO
pylcc.egg-info/SOURCES.txt
pylcc.egg-info/dependency_links.txt
pylcc.egg-info/entry_points.txt
pylcc.egg-info/requires.txt
pylcc.egg-info/top_level.txt
pylcc.egg-info/zip-safe