Metadata-Version: 1.1
Name: pylcc
Version: 0.3.4
Summary: pylcc is short for python libbpf compile collections
Home-page: https://gitee.com/anolis/surftrace
Author: liaozhaoyan
Author-email: zhaoyan.liao@linux.alibaba.com
License: MIT
Keywords: linux kernel trace
Platform: UNKNOWN
Classifier: Topic :: System :: Operating System Kernels :: Linux
Classifier: Programming Language :: Python
Classifier: Programming Language :: Python :: 2
Classifier: Programming Language :: Python :: 2.7
Classifier: Programming Language :: Python :: 3
Classifier: Programming Language :: Python :: 3.5
Classifier: Programming Language :: Python :: 3.6
Classifier: Programming Language :: Python :: 3.7
Classifier: Programming Language :: Python :: 3.8
Classifier: Programming Language :: Python :: 3.9
Classifier: Programming Language :: Python :: 3.10
Classifier: Programming Language :: Python :: Implementation :: PyPy
